{
  "schema_version": "2.0",
  "tier": "fund-views-raw",
  "generated_at": "2026-06-23",
  "description": "View phân bổ ngành FORWARD (nhóm nào nhận dòng tiền các quý tới) từ các tổ chức lớn ở Mỹ — báo cáo MỚI NHẤT công khai. Input thô do bước nghiên cứu web cập nhật mỗi quý; logic tổng hợp/đối chiếu ở scripts/build_fund_consensus.py (tất định). Đối chiếu với DỰ BÁO rotation tháng/quý tới của hệ thống (monthly_rotation_forecast_latest.json), KHÔNG trộn vào engine.",
  "tilt_scale": {
    "1": "Overweight / Positive / Undervalued (kỳ vọng nhận dòng tiền / vượt S&P 500)",
    "0": "Neutral / fair value",
    "-1": "Underweight / Negative / Overvalued (kỳ vọng kém / mất dòng tiền)",
    "null": "Báo cáo không nêu rõ (chưa verify) — KHÔNG bịa"
  },
  "lens_note": "lens='flow' = lăng kính phân bổ/dòng tiền (OW = sẽ nhận tiền). lens='value' = lăng kính định giá (Morningstar: undervalued = cơ hội — mang tính CONTRARIAN, lệch với engine momentum là tension bình thường, không phải mâu thuẫn).",
  "refresh_note": "Cập nhật mỗi quý qua nghiên cứu web. Sau khi sửa file này chạy: python scripts/build_fund_consensus.py",
  "sources": [
    {
      "fund": "J.P. Morgan",
      "report": "Mid-Year Outlook 2026 — Promise and Pressure",
      "as_of": "2026-06-15",
      "horizon": "6-12 tháng",
      "lens": "flow",
      "cadence": "semiannual",
      "url": "https://www.jpmorgan.com/content/dam/jpmorgan/documents/wealth-management/mid-year-outlook-2026.pdf",
      "verified": true,
      "coverage": "partial",
      "coverage_note": "Verify qua tóm tắt: OW US large-cap & growth, AI broadening. High-conviction 'power' → Industrials + Utilities bổ trợ Tech. Tech & Financials là tỷ trọng lớn nhất + kỳ vọng EPS mạnh. Sector khác không nêu rõ → null.",
      "views": {
        "XLK": {"tilt": 1, "label": "Overweight", "note": "Tỷ trọng lớn nhất; AI broadening, EPS mạnh"},
        "XLF": {"tilt": 1, "label": "Overweight", "note": "Tỷ trọng lớn + kỳ vọng lợi nhuận tốt"},
        "XLI": {"tilt": 1, "label": "Overweight", "note": "Theme 'power'/AI infra bổ trợ Tech"},
        "XLU": {"tilt": 1, "label": "Overweight", "note": "High-conviction 'power' — nhu cầu điện"},
        "XLC": {"tilt": null, "label": null, "note": null},
        "XLY": {"tilt": null, "label": null, "note": null},
        "XLB": {"tilt": null, "label": null, "note": null},
        "XLE": {"tilt": null, "label": null, "note": null},
        "XLV": {"tilt": null, "label": null, "note": null},
        "XLP": {"tilt": null, "label": null, "note": null},
        "XLRE": {"tilt": null, "label": null, "note": null}
      }
    },
    {
      "fund": "Goldman Sachs",
      "report": "2026 Equity Outlook — Tech Tonic: a Broadening Bull Market (+ 2026 themes)",
      "as_of": "2025-11-18",
      "horizon": "12 tháng",
      "lens": "flow",
      "cadence": "annual+updates",
      "url": "https://www.goldmansachs.com/insights/goldman-sachs-research/equity-outlook-2026-tech-tonic-a-broadening-bull-market",
      "verified": true,
      "coverage": "partial",
      "coverage_note": "Year-ahead outlook (sẽ stale — cần đọc bản mid-year khi có). Themes verify: Tech (AI infra: memory/connectors), Healthcare (GLP-1, 'cardiology renaissance'), beneficiaries của deregulation: Financials, Energy, pharma. Broadening bull (đa dạng hoá sang value/sector khác).",
      "views": {
        "XLK": {"tilt": 1, "label": "Overweight", "note": "AI infra (memory, connectors, data center)"},
        "XLV": {"tilt": 1, "label": "Overweight", "note": "GLP-1/obesity, cardiology renaissance"},
        "XLF": {"tilt": 1, "label": "Overweight", "note": "Hưởng lợi deregulation"},
        "XLE": {"tilt": 1, "label": "Overweight", "note": "Hưởng lợi deregulation"},
        "XLC": {"tilt": null, "label": null, "note": null},
        "XLI": {"tilt": null, "label": null, "note": null},
        "XLY": {"tilt": null, "label": null, "note": null},
        "XLB": {"tilt": null, "label": null, "note": null},
        "XLU": {"tilt": null, "label": null, "note": null},
        "XLP": {"tilt": null, "label": null, "note": null},
        "XLRE": {"tilt": null, "label": null, "note": null}
      }
    },
    {
      "fund": "State Street SPDR",
      "report": "Sector Market Perspectives — Q2 2026",
      "as_of": "2026-04-08",
      "horizon": "6-12 tháng",
      "lens": "flow",
      "cadence": "quarterly",
      "url": "https://www.ssga.com/us/en/individual/insights/sector-market-perspectives-q2-2026",
      "verified": true,
      "coverage": "full",
      "views": {
        "XLK": {"tilt": 1, "label": "Positive", "note": "AI-driven earnings rộng + định giá hấp dẫn sau nhịp chỉnh"},
        "XLC": {"tilt": 1, "label": "Positive", "note": "Quảng cáo số tăng tốc + AI monetization"},
        "XLI": {"tilt": 1, "label": "Positive", "note": "CapEx AI infra, quốc phòng, chính sách tài khoá pro-CapEx"},
        "XLB": {"tilt": 1, "label": "Positive", "note": "Cân bằng cung-cầu hoá chất, nhu cầu kim loại cấu trúc"},
        "XLE": {"tilt": 1, "label": "Positive", "note": "Rủi ro gián đoạn nguồn cung kéo dài, premium địa chính trị"},
        "XLU": {"tilt": 1, "label": "Positive", "note": "Nhu cầu điện AI, điện khí hoá, reshoring"},
        "XLF": {"tilt": 0, "label": "Neutral", "note": "Trì hoãn cắt lãi suất bù trừ định giá cải thiện"},
        "XLV": {"tilt": 0, "label": "Neutral", "note": "Tăng trưởng lợi nhuận chậm, ít catalyst dù định giá rẻ"},
        "XLY": {"tilt": -1, "label": "Negative", "note": "Thu nhập thực yếu, tiết kiệm thấp ép cầu"},
        "XLP": {"tilt": -1, "label": "Negative", "note": "Áp lực biên lợi nhuận, tăng trưởng yếu"},
        "XLRE": {"tilt": -1, "label": "Negative", "note": "Momentum lợi nhuận yếu + giảm kỳ vọng cắt lãi suất"}
      }
    },
    {
      "fund": "Morningstar",
      "report": "US Stock Market Outlook — Where to Find Value (mid-June 2026)",
      "as_of": "2026-06-15",
      "horizon": "định giá hiện tại (chỉ báo forward value)",
      "lens": "value",
      "cadence": "monthly/quarterly",
      "url": "https://www.morningstar.com/markets/us-stock-market-outlook-where-find-value-after-aprils-rally",
      "verified": true,
      "coverage": "partial",
      "coverage_note": "Lăng kính ĐỊNH GIÁ (price/fair value). Undervalued=cơ hội (CONTRARIAN với momentum). Verify: Tech -11% (rẻ nhất), Healthcare -7%, Financials -5%, Real Estate -5% (undervalued); Consumer Defensive +19% (đắt nhất), Basic Materials +12%, Industrials +8% (overvalued). Energy/Utilities/Comm/ConsDisc không nêu số → null.",
      "views": {
        "XLK": {"tilt": 1, "label": "Undervalued -11%", "note": "Rẻ nhất so với fair value"},
        "XLV": {"tilt": 1, "label": "Undervalued -7%", "note": "Medical devices/diagnostics (DHR, MDT, ABT)"},
        "XLF": {"tilt": 1, "label": "Undervalued -5%", "note": "Discount so với fair value"},
        "XLRE": {"tilt": 1, "label": "Undervalued -5%", "note": "Discount so với fair value"},
        "XLP": {"tilt": -1, "label": "Overvalued +19%", "note": "Đắt nhất (WMT/COST 1-sao kéo)"},
        "XLB": {"tilt": -1, "label": "Overvalued +12%", "note": "Đã tăng ~14% YTD"},
        "XLI": {"tilt": -1, "label": "Overvalued +8%", "note": "Tăng ~17% YTD nhờ AI-buildout"},
        "XLE": {"tilt": null, "label": null, "note": null},
        "XLU": {"tilt": null, "label": null, "note": null},
        "XLC": {"tilt": null, "label": null, "note": null},
        "XLY": {"tilt": null, "label": null, "note": null}
      }
    }
  ]
}
